demutil/__init__.py
demutil/image.py
demutil/loader.py
demutil/processor.py
demutil/util.py
dem_util-1.0.4.dist-info/LICENSE
dem_util-1.0.4.dist-info/METADATA
dem_util-1.0.4.dist-info/WHEEL
dem_util-1.0.4.dist-info/top_level.txt
dem_util-1.0.4.dist-info/RECORD
